{
  "x-generator": "NSwag v14.1.0.0 (NJsonSchema v11.0.2.0 (Newtonsoft.Json v13.0.0.0))",
  "openapi": "3.0.0",
  "info": {
    "title": "CleanArchitecture API",
    "version": "1.0.0"
  },
  "servers": [
    {
      "url": "/api"
    }
  ],
  "paths": {
    "/ProblemCatalogs": {
      "post": {
        "tags": [
          "ProblemCatalogs"
        ],
        "operationId": "ProblemCatalogs_Create",
        "requestBody": {
          "x-name": "command",
          "content": {
            "application/json": {
              "schema": {
                "$ref": "#/components/schemas/CreateProblemCatalogCommand"
              }
            }
          },
          "required": true,
          "x-position": 1
        },
        "responses": {
          "200": {
            "description": "",
            "content": {
              "application/json": {
                "schema": {
                  "type": "integer",
                  "format": "int32"
                }
              }
            }
          }
        }
      },
      "delete": {
        "tags": [
          "ProblemCatalogs"
        ],
        "operationId": "ProblemCatalogs_DeleteProblemCatalogs",
        "requestBody": {
          "x-name": "deleteProblemCatalogsCommand",
          "content": {
            "application/json": {
              "schema": {
                "$ref": "#/components/schemas/DeleteProblemCatalogsCommand"
              }
            }
          },
          "required": true,
          "x-position": 1
        },
        "responses": {
          "204": {
            "description": ""
          },
          "default": {
            "description": "",
            "content": {
              "application/json": {
                "schema": {
                  "$ref": "#/components/schemas/ProblemDetails"
                }
              }
            }
          }
        }
      }
    },
    "/ProblemCatalogs/{id}": {
      "put": {
        "tags": [
          "ProblemCatalogs"
        ],
        "operationId": "ProblemCatalogs_Update",
        "parameters": [
          {
            "name": "id",
            "in": "path",
            "required": true,
            "schema": {
              "type": "integer",
              "format": "int32"
            },
            "x-position": 1
          }
        ],
        "requestBody": {
          "x-name": "command",
          "content": {
            "application/json": {
              "schema": {
                "$ref": "#/components/schemas/UpdateProblemCatalogCommand"
              }
            }
          },
          "required": true,
          "x-position": 2
        },
        "responses": {
          "204": {
            "description": ""
          },
          "400": {
            "description": "",
            "content": {
              "application/json": {
                "schema": {
                  "$ref": "#/components/schemas/ProblemDetails"
                }
              }
            }
          },
          "default": {
            "description": "",
            "content": {
              "application/json": {
                "schema": {
                  "$ref": "#/components/schemas/ProblemDetails"
                }
              }
            }
          }
        }
      },
      "delete": {
        "tags": [
          "ProblemCatalogs"
        ],
        "operationId": "ProblemCatalogs_Delete",
        "parameters": [
          {
            "name": "id",
            "in": "path",
            "required": true,
            "schema": {
              "type": "integer",
              "format": "int32"
            },
            "x-position": 1
          }
        ],
        "responses": {
          "204": {
            "description": ""
          },
          "default": {
            "description": "",
            "content": {
              "application/json": {
                "schema": {
                  "$ref": "#/components/schemas/ProblemDetails"
                }
              }
            }
          }
        }
      }
    },
    "/ProblemCategories": {
      "post": {
        "tags": [
          "ProblemCategories"
        ],
        "operationId": "ProblemCategories_Create",
        "requestBody": {
          "x-name": "command",
          "content": {
            "application/json": {
              "schema": {
                "$ref": "#/components/schemas/CreateProblemCategoryCommand"
              }
            }
          },
          "required": true,
          "x-position": 1
        },
        "responses": {
          "200": {
            "description": "",
            "content": {
              "application/json": {
                "schema": {
                  "type": "integer",
                  "format": "int32"
                }
              }
            }
          }
        }
      },
      "delete": {
        "tags": [
          "ProblemCategories"
        ],
        "operationId": "ProblemCategories_DeleteProblemCategories",
        "requestBody": {
          "x-name": "deleteProblemCategoriesCommand",
          "content": {
            "application/json": {
              "schema": {
                "$ref": "#/components/schemas/DeleteProblemCategoriesCommand"
              }
            }
          },
          "required": true,
          "x-position": 1
        },
        "responses": {
          "204": {
            "description": ""
          },
          "default": {
            "description": "",
            "content": {
              "application/json": {
                "schema": {
                  "$ref": "#/components/schemas/ProblemDetails"
                }
              }
            }
          }
        }
      }
    },
    "/ProblemCategories/{id}": {
      "put": {
        "tags": [
          "ProblemCategories"
        ],
        "operationId": "ProblemCategories_Update",
        "parameters": [
          {
            "name": "id",
            "in": "path",
            "required": true,
            "schema": {
              "type": "integer",
              "format": "int32"
            },
            "x-position": 1
          }
        ],
        "requestBody": {
          "x-name": "command",
          "content": {
            "application/json": {
              "schema": {
                "$ref": "#/components/schemas/UpdateProblemCategoryCommand"
              }
            }
          },
          "required": true,
          "x-position": 2
        },
        "responses": {
          "204": {
            "description": ""
          },
          "400": {
            "description": "",
            "content": {
              "application/json": {
                "schema": {
                  "$ref": "#/components/schemas/ProblemDetails"
                }
              }
            }
          },
          "default": {
            "description": "",
            "content": {
              "application/json": {
                "schema": {
                  "$ref": "#/components/schemas/ProblemDetails"
                }
              }
            }
          }
        }
      },
      "delete": {
        "tags": [
          "ProblemCategories"
        ],
        "operationId": "ProblemCategories_Delete",
        "parameters": [
          {
            "name": "id",
            "in": "path",
            "required": true,
            "schema": {
              "type": "integer",
              "format": "int32"
            },
            "x-position": 1
          }
        ],
        "responses": {
          "204": {
            "description": ""
          },
          "default": {
            "description": "",
            "content": {
              "application/json": {
                "schema": {
                  "$ref": "#/components/schemas/ProblemDetails"
                }
              }
            }
          }
        }
      }
    },
    "/Problems": {
      "get": {
        "tags": [
          "Problems"
        ],
        "operationId": "Problems_GetProblems",
        "parameters": [
          {
            "name": "query",
            "in": "query",
            "schema": {
              "$ref": "#/components/schemas/GetProblemsQuery"
            },
            "x-position": 1
          }
        ],
        "responses": {
          "200": {
            "description": "",
            "content": {
              "application/json": {
                "schema": {
                  "$ref": "#/components/schemas/ProblemsDto"
                }
              }
            }
          }
        }
      },
      "post": {
        "tags": [
          "Problems"
        ],
        "operationId": "Problems_Create",
        "requestBody": {
          "x-name": "command",
          "content": {
            "application/json": {
              "schema": {
                "$ref": "#/components/schemas/CreateProblemCommand"
              }
            }
          },
          "required": true,
          "x-position": 1
        },
        "responses": {
          "200": {
            "description": "",
            "content": {
              "application/json": {
                "schema": {
                  "type": "integer",
                  "format": "int32"
                }
              }
            }
          }
        }
      },
      "delete": {
        "tags": [
          "Problems"
        ],
        "operationId": "Problems_DeleteProblems",
        "requestBody": {
          "x-name": "deleteProblemsCommand",
          "content": {
            "application/json": {
              "schema": {
                "$ref": "#/components/schemas/DeleteProblemsCommand"
              }
            }
          },
          "required": true,
          "x-position": 1
        },
        "responses": {
          "204": {
            "description": ""
          },
          "default": {
            "description": "",
            "content": {
              "application/json": {
                "schema": {
                  "$ref": "#/components/schemas/ProblemDetails"
                }
              }
            }
          }
        }
      }
    },
    "/Problems/{id}": {
      "put": {
        "tags": [
          "Problems"
        ],
        "operationId": "Problems_Update",
        "parameters": [
          {
            "name": "id",
            "in": "path",
            "required": true,
            "schema": {
              "type": "integer",
              "format": "int32"
            },
            "x-position": 1
          }
        ],
        "requestBody": {
          "x-name": "command",
          "content": {
            "application/json": {
              "schema": {
                "$ref": "#/components/schemas/UpdateProblemCommand"
              }
            }
          },
          "required": true,
          "x-position": 2
        },
        "responses": {
          "204": {
            "description": ""
          },
          "400": {
            "description": "",
            "content": {
              "application/json": {
                "schema": {
                  "$ref": "#/components/schemas/ProblemDetails"
                }
              }
            }
          },
          "default": {
            "description": "",
            "content": {
              "application/json": {
                "schema": {
                  "$ref": "#/components/schemas/ProblemDetails"
                }
              }
            }
          }
        }
      },
      "delete": {
        "tags": [
          "Problems"
        ],
        "operationId": "Problems_Delete",
        "parameters": [
          {
            "name": "id",
            "in": "path",
            "required": true,
            "schema": {
              "type": "integer",
              "format": "int32"
            },
            "x-position": 1
          }
        ],
        "responses": {
          "204": {
            "description": ""
          },
          "default": {
            "description": "",
            "content": {
              "application/json": {
                "schema": {
                  "$ref": "#/components/schemas/ProblemDetails"
                }
              }
            }
          }
        }
      }
    }
  },
  "components": {
    "schemas": {
      "CreateProblemCatalogCommand": {
        "type": "object",
        "additionalProperties": false,
        "required": [
          "name"
        ],
        "properties": {
          "name": {
            "type": "string",
            "maxLength": 255,
            "minLength": 1,
            "nullable": false
          },
          "description": {
            "type": "string",
            "maxLength": 1500,
            "minLength": 0,
            "nullable": true
          }
        }
      },
      "ProblemDetails": {
        "type": "object",
        "additionalProperties": {
          "nullable": true
        },
        "properties": {
          "type": {
            "type": "string",
            "nullable": true
          },
          "title": {
            "type": "string",
            "nullable": true
          },
          "status": {
            "type": "integer",
            "format": "int32",
            "nullable": true
          },
          "detail": {
            "type": "string",
            "nullable": true
          },
          "instance": {
            "type": "string",
            "nullable": true
          },
          "extensions": {
            "type": "object",
            "additionalProperties": {}
          }
        }
      },
      "UpdateProblemCatalogCommand": {
        "type": "object",
        "additionalProperties": false,
        "required": [
          "name"
        ],
        "properties": {
          "id": {
            "type": "integer",
            "format": "int32"
          },
          "name": {
            "type": "string",
            "maxLength": 255,
            "minLength": 1,
            "nullable": false
          },
          "description": {
            "type": "string",
            "maxLength": 1500,
            "minLength": 0,
            "nullable": true
          }
        }
      },
      "DeleteProblemCatalogsCommand": {
        "type": "object",
        "additionalProperties": false,
        "properties": {
          "ids": {
            "type": "array",
            "items": {
              "type": "integer",
              "format": "int32"
            }
          }
        }
      },
      "CreateProblemCategoryCommand": {
        "type": "object",
        "additionalProperties": false,
        "required": [
          "name"
        ],
        "properties": {
          "name": {
            "type": "string",
            "maxLength": 255,
            "minLength": 1,
            "nullable": false
          },
          "description": {
            "type": "string",
            "maxLength": 1500,
            "minLength": 0,
            "nullable": true
          },
          "problemCatalogId": {
            "type": "integer",
            "format": "int32",
            "nullable": true
          }
        }
      },
      "UpdateProblemCategoryCommand": {
        "type": "object",
        "additionalProperties": false,
        "required": [
          "name"
        ],
        "properties": {
          "id": {
            "type": "integer",
            "format": "int32"
          },
          "name": {
            "type": "string",
            "maxLength": 255,
            "minLength": 1,
            "nullable": false
          },
          "description": {
            "type": "string",
            "maxLength": 1500,
            "minLength": 0,
            "nullable": true
          },
          "problemCatalogId": {
            "type": "integer",
            "format": "int32",
            "nullable": true
          }
        }
      },
      "DeleteProblemCategoriesCommand": {
        "type": "object",
        "additionalProperties": false,
        "properties": {
          "ids": {
            "type": "array",
            "items": {
              "type": "integer",
              "format": "int32"
            }
          }
        }
      },
      "ProblemsDto": {
        "type": "object",
        "additionalProperties": false,
        "properties": {
          "problemCatalogs": {
            "type": "array",
            "items": {
              "$ref": "#/components/schemas/ProblemCatalogDto"
            }
          },
          "problemCategories": {
            "type": "array",
            "items": {
              "$ref": "#/components/schemas/ProblemCategoryDto"
            }
          },
          "problems": {
            "type": "array",
            "items": {
              "$ref": "#/components/schemas/ProblemDto"
            }
          }
        }
      },
      "ProblemCatalogDto": {
        "type": "object",
        "additionalProperties": false,
        "properties": {
          "id": {
            "type": "integer",
            "format": "int32"
          },
          "name": {
            "type": "string"
          },
          "description": {
            "type": "string",
            "nullable": true
          },
          "problemCategories": {
            "type": "array",
            "items": {
              "$ref": "#/components/schemas/ProblemCategory"
            }
          }
        }
      },
      "ProblemCategory": {
        "allOf": [
          {
            "$ref": "#/components/schemas/BaseAuditableEntity"
          },
          {
            "type": "object",
            "additionalProperties": false,
            "properties": {
              "name": {
                "type": "string"
              },
              "description": {
                "type": "string",
                "nullable": true
              },
              "problemCatalogId": {
                "type": "integer",
                "format": "int32",
                "nullable": true
              },
              "problems": {
                "type": "array",
                "items": {
                  "$ref": "#/components/schemas/Problem"
                }
              }
            }
          }
        ]
      },
      "Problem": {
        "allOf": [
          {
            "$ref": "#/components/schemas/BaseAuditableEntity"
          },
          {
            "type": "object",
            "additionalProperties": false,
            "properties": {
              "name": {
                "type": "string"
              },
              "description": {
                "type": "string",
                "nullable": true
              },
              "problemCategoryId": {
                "type": "integer",
                "format": "int32",
                "nullable": true
              }
            }
          }
        ]
      },
      "BaseAuditableEntity": {
        "allOf": [
          {
            "$ref": "#/components/schemas/BaseEntity"
          },
          {
            "type": "object",
            "x-abstract": true,
            "additionalProperties": false,
            "properties": {
              "created": {
                "type": "string",
                "format": "date-time"
              },
              "lastModified": {
                "type": "string",
                "format": "date-time",
                "nullable": true
              },
              "lastModifiedBy": {
                "type": "string",
                "nullable": true
              }
            }
          }
        ]
      },
      "BaseEntity": {
        "type": "object",
        "x-abstract": true,
        "additionalProperties": false,
        "properties": {
          "id": {
            "type": "integer",
            "format": "int32"
          },
          "domainEvents": {
            "type": "array",
            "items": {
              "$ref": "#/components/schemas/BaseEvent"
            }
          }
        }
      },
      "BaseEvent": {
        "type": "object",
        "x-abstract": true,
        "additionalProperties": false
      },
      "ProblemCategoryDto": {
        "type": "object",
        "additionalProperties": false,
        "properties": {
          "id": {
            "type": "integer",
            "format": "int32"
          },
          "name": {
            "type": "string"
          },
          "description": {
            "type": "string",
            "nullable": true
          },
          "problemCatalogId": {
            "type": "integer",
            "format": "int32",
            "nullable": true
          },
          "problems": {
            "type": "array",
            "items": {
              "$ref": "#/components/schemas/ProblemDto"
            }
          }
        }
      },
      "ProblemDto": {
        "type": "object",
        "additionalProperties": false,
        "properties": {
          "id": {
            "type": "integer",
            "format": "int32"
          },
          "name": {
            "type": "string"
          },
          "description": {
            "type": "string",
            "nullable": true
          },
          "problemCategoryId": {
            "type": "integer",
            "format": "int32",
            "nullable": true
          }
        }
      },
      "GetProblemsQuery": {
        "type": "object",
        "additionalProperties": false
      },
      "CreateProblemCommand": {
        "type": "object",
        "additionalProperties": false,
        "required": [
          "name"
        ],
        "properties": {
          "name": {
            "type": "string",
            "maxLength": 255,
            "minLength": 1,
            "nullable": false
          },
          "description": {
            "type": "string",
            "maxLength": 1500,
            "minLength": 0,
            "nullable": true
          },
          "problemCategoryId": {
            "type": "integer",
            "format": "int32",
            "nullable": true
          }
        }
      },
      "UpdateProblemCommand": {
        "type": "object",
        "additionalProperties": false,
        "required": [
          "name"
        ],
        "properties": {
          "id": {
            "type": "integer",
            "format": "int32"
          },
          "name": {
            "type": "string",
            "maxLength": 255,
            "minLength": 1,
            "nullable": false
          },
          "description": {
            "type": "string",
            "maxLength": 1500,
            "minLength": 0,
            "nullable": true
          },
          "problemCategoryId": {
            "type": "integer",
            "format": "int32",
            "nullable": true
          }
        }
      },
      "DeleteProblemsCommand": {
        "type": "object",
        "additionalProperties": false,
        "properties": {
          "ids": {
            "type": "array",
            "items": {
              "type": "integer",
              "format": "int32"
            }
          }
        }
      }
    }
  }
}